setup.py
new_python/__init__.py
new_python/creator.py
new_python/template.py
new_python.egg-info/PKG-INFO
new_python.egg-info/SOURCES.txt
new_python.egg-info/dependency_links.txt
new_python.egg-info/not-zip-safe
new_python.egg-info/top_level.txt