Metadata-Version: 1.0
Name: new-python
Version: 0.2
Summary: Default template engine for python.
Home-page: https://github.com/hammacktony/new_python.git
Author: Tony Hammack
Author-email: hammack.tony@gmail.com
License: MIT
Platform: UNKNOWN
